ethereum_dasm/__init__.py
ethereum_dasm/__main__.py
ethereum_dasm/evmdasm.py
ethereum_dasm/asm/__init__.py
ethereum_dasm/asm/instructions.py
ethereum_dasm/asm/registry.py
ethereum_dasm/output/__init__.py
ethereum_dasm/output/console.py
ethereum_dasm/symbolic/__init__.py
ethereum_dasm/symbolic/mythril.py
ethereum_dasm/symbolic/simplify.py
ethereum_dasm/utils/__init__.py
ethereum_dasm/utils/api.py
ethereum_dasm/utils/colors.py
ethereum_dasm/utils/data.py
ethereum_dasm/utils/signatures.py
ethereum_dasm-0.1.5.dist-info/LICENSE
ethereum_dasm-0.1.5.dist-info/METADATA
ethereum_dasm-0.1.5.dist-info/WHEEL
ethereum_dasm-0.1.5.dist-info/top_level.txt
ethereum_dasm-0.1.5.dist-info/RECORD
