Metadata-Version: 2.1
Name: ethereum-dasm
Version: 0.1.5
Summary: An ethereum bytecode disassembler with static and dynamic analysis features
Home-page: https://github.com/tintinweb/ethereum-dasm
Author: tintinweb
Author-email: tintinweb@oststrom.com
License: GPLv2
Download-URL: https://github.com/tintinweb/ethereum-dasm/tarball/v0.1.5
Keywords: ethereum,blockchain,evm,disassembler,decompiler,pseudocode
Platform: UNKNOWN
Requires-Dist: evmdasm
Requires-Dist: colorama
Requires-Dist: requests
Requires-Dist: tabulate
Provides-Extra: abidecoder
Requires-Dist: ethereum-input-decoder ; extra == 'abidecoder'
Requires-Dist: pyetherchain ; extra == 'abidecoder'
Provides-Extra: mythril
Requires-Dist: mythril ; extra == 'mythril'
